examples/__init__.py
examples/full_demo.py
sharingan/__init__.py
sharingan/cli.py
sharingan/exceptions.py
sharingan/processor.py
sharingan/chat/__init__.py
sharingan/chat/llm.py
sharingan/embedding/__init__.py
sharingan/embedding/compressor.py
sharingan/embedding/semantic_graph.py
sharingan/events/__init__.py
sharingan/events/detector.py
sharingan/events/segmenter.py
sharingan/query/__init__.py
sharingan/query/nl_query.py
sharingan/query/retriever.py
sharingan/storage/__init__.py
sharingan/storage/embedding_store.py
sharingan/temporal/__init__.py
sharingan/temporal/engine.py
sharingan/temporal/gating.py
sharingan/temporal/memory_tokens.py
sharingan/temporal/motion_pooling.py
sharingan/temporal/tas.py
sharingan/temporal/tda.py
sharingan/tracking/__init__.py
sharingan/tracking/entities.py
sharingan/tracking/tracker.py
sharingan/ui/__init__.py
sharingan/ui/app.py
sharingan/ui/templates/index.html
sharingan/ui/templates/player.html
sharingan/utils/__init__.py
sharingan/utils/config.py
sharingan/utils/flow.py
sharingan/utils/hardware.py
sharingan/video/__init__.py
sharingan/video/api.py
sharingan/video/loader.py
sharingan/video/sampler.py
sharingan/vlm/__init__.py
sharingan/vlm/encoder.py
sharingan/vlm/lightweight_head.py
sharingan/vlm/smolvlm.py
sharingan_core-3.0.0.dist-info/licenses/LICENSE
tests/__init__.py
sharingan_core-3.0.0.dist-info/METADATA
sharingan_core-3.0.0.dist-info/WHEEL
sharingan_core-3.0.0.dist-info/top_level.txt
sharingan_core-3.0.0.dist-info/RECORD
