Metadata-Version: 2.4
Name: sharingan-core
Version: 3.0.0
Summary: OpenCV for Semantic Video Understanding with Temporal Reasoning
Home-page: https://github.com/skhavindev/sharingan
Author: Sharingan Contributors
Author-email: 
License: MIT
Project-URL: Homepage, https://github.com/sharingan/sharingan
Project-URL: Documentation, https://sharingan.readthedocs.io
Project-URL: Repository, https://github.com/sharingan/sharingan
Project-URL: Issues, https://github.com/sharingan/sharingan/issues
Keywords: video,computer-vision,vlm,temporal-reasoning,semantic-understanding
Classifier: Development Status :: 3 - Alpha
Classifier: Intended Audience :: Developers
Classifier: Intended Audience :: Science/Research
Classifier: License :: OSI Approved :: MIT License
Classifier: Programming Language :: Python :: 3
Classifier: Programming Language :: Python :: 3.8
Classifier: Programming Language :: Python :: 3.9
Classifier: Programming Language :: Python :: 3.10
Classifier: Programming Language :: Python :: 3.11
Classifier: Topic :: Scientific/Engineering :: Artificial Intelligence
Classifier: Topic :: Multimedia :: Video
Requires-Python: >=3.8
License-File: LICENSE
Requires-Dist: numpy>=1.20.0
Requires-Dist: opencv-python>=4.5.0
Requires-Dist: torch>=1.10.0
Requires-Dist: torchvision>=0.11.0
Requires-Dist: Pillow>=8.0.0
Requires-Dist: tqdm>=4.60.0
Requires-Dist: pyyaml>=5.4.0
Provides-Extra: full
Requires-Dist: transformers>=4.20.0; extra == "full"
Requires-Dist: faiss-cpu>=1.7.0; extra == "full"
Requires-Dist: decord>=0.6.0; extra == "full"
Provides-Extra: gpu
Requires-Dist: faiss-gpu>=1.7.0; extra == "gpu"
Provides-Extra: dev
Requires-Dist: pytest>=7.0.0; extra == "dev"
Requires-Dist: pytest-cov>=3.0.0; extra == "dev"
Requires-Dist: black>=22.0.0; extra == "dev"
Requires-Dist: mypy>=0.950; extra == "dev"
Requires-Dist: flake8>=4.0.0; extra == "dev"
Provides-Extra: docs
Requires-Dist: sphinx>=4.5.0; extra == "docs"
Requires-Dist: sphinx-rtd-theme>=1.0.0; extra == "docs"
Dynamic: home-page
Dynamic: license-file
Dynamic: requires-python
